README.md
setup.py
autocheckinsurance/__init__.py
autocheckinsurance/api_client.py
autocheckinsurance/configuration.py
autocheckinsurance/rest.py
autocheckinsurance/api/__init__.py
autocheckinsurance/api/default_api.py
autocheckinsurance/api/vehicle_api.py
autocheckinsurance/api/vehicle_history_api.py
autocheckinsurance/models/__init__.py
autocheckinsurance/models/empty.py
autocheckinsurance/models/history_record.py
autocheckinsurance/models/history_request.py
autocheckinsurance/models/history_response.py
autocheckinsurance/models/recall_record.py
autocheckinsurance/models/risk_calculation_plus_response.py
autocheckinsurance/models/risk_calculation_request.py
autocheckinsurance/models/risk_calculation_response.py
autocheckinsurance/models/unprocessed_history_requests.py
autocheckinsurance/models/unprocessed_risk_calculation_requests.py
autocheckinsurance/models/vehicle.py
autocheckinsurance/models/vehicle_history.py
autocheckinsurance/models/vehicle_information.py
autocheckinsurance/models/vehicle_ownership_activity.py
autocheckinsurance/models/vehicle_recall.py
autocheckinsurance/models/vehicle_request_attribute.py
autocheckinsurance/models/vehicle_risk_request_attribute.py
autocheckinsurance/models/vehicle_risk_result.py
autocheckinsurance/models/vehicle_scoring.py
autocheckinsurance_api_python_client.egg-info/PKG-INFO
autocheckinsurance_api_python_client.egg-info/SOURCES.txt
autocheckinsurance_api_python_client.egg-info/dependency_links.txt
autocheckinsurance_api_python_client.egg-info/requires.txt
autocheckinsurance_api_python_client.egg-info/top_level.txt
test/__init__.py
test/test_default_api.py
test/test_empty.py
test/test_history_record.py
test/test_history_request.py
test/test_history_response.py
test/test_recall_record.py
test/test_risk_calculation_plus_response.py
test/test_risk_calculation_request.py
test/test_risk_calculation_response.py
test/test_unprocessed_history_requests.py
test/test_unprocessed_risk_calculation_requests.py
test/test_vehicle.py
test/test_vehicle_api.py
test/test_vehicle_history.py
test/test_vehicle_history_api.py
test/test_vehicle_information.py
test/test_vehicle_ownership_activity.py
test/test_vehicle_recall.py
test/test_vehicle_request_attribute.py
test/test_vehicle_risk_request_attribute.py
