Metadata-Version: 1.0
Name: autocheckinsurance-api-python-client
Version: 2.0.2
Summary: ACI Services API
Home-page: UNKNOWN
Author: UNKNOWN
Author-email: UNKNOWN
License: UNKNOWN
Keywords: Swagger,ACI Services API
Platform: UNKNOWN
